{
    "id": "e4c7a6e7-1335-430c-ab23-1d5792d47632",
    "name": "Masarak_Local",
    "values": [
        {
            "key": "baseUrl",
            "value": "https://localhost:49179",
            "type": "default",
            "enabled": true
        },
        {
            "key": "adminAccessToken",
            "value": "",
            "type": "default",
            "enabled": true
        },
        {
            "key": "parentAccessToken",
            "value": "",
            "type": "default",
            "enabled": true
        },
        {
            "key": "studentAccessToken",
            "value": "",
            "type": "default",
            "enabled": true
        }
    ],
    "_postman_variable_scope": "environment"
}